{
  "HomepageLocation": "https://www.google.com",
  "HomepageIsNewTabPage": false,
  "DefaultBrowserSettingEnabled": true,
  "RestoreOnStartup": 1,
  "SafeBrowsingProtectionLevel": 1,
  "MaxConnectionsPerProxy": 99,
  "ExtensionInstallForcelist": [
    "noondiphcddnnabmjcihcjfbhfklnnep",
    "djflhoibgkdhkhhcedjiklpkjnoahfmg"
  ],
  "ManagedBookmarks": [
    {
      "toplevel_name": "My managed bookmarks folder"
    },
    {
      "name": "Google",
      "url": "google.com"
    },
    {
      "name": "Youtube",
      "url": "youtube.com"
    },
    {
      "children": [
        {
          "name": "Chromium",
          "url": "chromium.org"
        },
        {
          "name": "Chromium Developers",
          "url": "dev.chromium.org"
        }
      ],
      "name": "Chrome links"
    }
  ]
}
