{
  "meta": {
    "customer_id": "customers/C0xxxxxxx",
    "exported_at": "2026-03-08 13:00:00.000000",
    "format": "cep_dlp_chrome_export",
    "total_items": 4
  },
  "dlp_configurations": {
    "regex_detectors": [
      {
        "name": "policies/aoajj264newreg123abc",
        "policyQuery": {
          "orgUnit": "orgUnits/03ph8a2zXXXXXXX",
          "sortOrder": 1
        },
        "setting": {
          "type": "settings/detector.regular_expression",
          "value": {
            "displayName": "API Key Pattern Detection",
            "regularExpression": {
              "expression": "(?i)(api[\\-_]?key|secret[\\-_]?key)\\s*[=:]\\s*[\"'][a-zA-Z0-9]{20,40}[\"']"
            }
          }
        },
        "type": "ADMIN"
      }
    ],
    "word_list_detectors": [
      {
        "name": "policies/aoajj264newwrd456def",
        "policyQuery": {
          "orgUnit": "orgUnits/03ph8a2zXXXXXXX",
          "sortOrder": 1
        },
        "setting": {
          "type": "settings/detector.word_list",
          "value": {
            "displayName": "Confidential Project Codenames",
            "wordList": {
              "words": [
                "Project Apollo",
                "Titan Initiative",
                "Operation Zeus"
              ]
            }
          }
        },
        "type": "ADMIN"
      }
    ],
    "url_list_detectors": [
      {
        "name": "policies/aoajj264newurl789ghi",
        "policyQuery": {
          "orgUnit": "orgUnits/03ph8a2zXXXXXXX",
          "sortOrder": 1
        },
        "setting": {
          "type": "settings/detector.url_list",
          "value": {
            "displayName": "Personal Cloud Storage Sites",
            "urlList": {
              "urls": [
                "dropbox.com",
                "box.com",
                "onedrive.live.com",
                "mega.nz"
              ]
            }
          }
        },
        "type": "ADMIN"
      }
    ],
    "rules": [
      {
        "name": "policies/akajj264newrul012jkl",
        "policyQuery": {
          "query": "entity.groups.exists(group, group.group_id == groupId('041mghmXXXXXXXX'))",
          "sortOrder": 1
        },
        "setting": {
          "type": "settings/rule.dlp",
          "value": {
            "displayName": "AUS Block Code Uploads to Personal Storage",
            "description": "Prevents engineers from uploading code or API keys to personal cloud storage.",
            "state": "ACTIVE",
            "triggers": [
              "google.workspace.chrome.file.v1.upload",
              "google.workspace.chrome.web_content.v1.upload"
            ],
            "condition": {
              "contentCondition": "(all_content.matches_dlp_detector('DOCUMENT_TYPE/R&D/SOURCE_CODE', google.privacy.dlp.v2.Likelihood.LIKELY, {minimum_match_count: 1, minimum_unique_match_count: 1}) || all_content.matches_regex_detector('policies/aoajj264newreg123abc', {minimum_match_count: 1})) && url.matches_url_list('policies/aoajj264newurl789ghi')"
            },
            "action": {
              "chromeAction": {
                "blockContent": {
                  "actionParams": {
                    "customEndUserMessage": {
                      "unsafeHtmlMessageBody": "Upload of Source Code or API Keys to non-corporate cloud storage is strictly prohibited."
                    },
                    "saveContent": true
                  }
                }
              }
            }
          }
        },
        "type": "ADMIN"
      }
    ]
  }
}
